mcp_server_searxng/SearXNGServer.py
mcp_server_searxng/__init__.py
mcp_server_searxng/__main__.py
mcp_server_searxng/searXNG_client.py
mcp_server_searxng-0.2.dist-info/licenses/LICENSE
mcp_server_searxng-0.2.dist-info/METADATA
mcp_server_searxng-0.2.dist-info/WHEEL
mcp_server_searxng-0.2.dist-info/top_level.txt
mcp_server_searxng-0.2.dist-info/RECORD
