Metadata-Version: 2.4
Name: mcp_server_searxng
Version: 0.2
Summary: 基于MCP技术的SearXNG搜索引擎服务器
Home-page: https://github.com/panxingfeng/mcp_server_searXNG
Download-URL: https://github.com/panxingfeng/mcp_server_searXNG/archive/refs/tags/0.1.tar.gz
Author: panxingfeng
Author-email: 1115005803@qq.com
License: MIT
Keywords: searXNG,mcp,search,automation
Classifier: Development Status :: 3 - Alpha
Classifier: Intended Audience :: Developers
Classifier: Topic :: Internet :: WWW/HTTP :: Indexing/Search
Classifier: Topic :: Software Development :: Libraries :: Python Modules
Classifier: Topic :: Utilities
Classifier: License :: OSI Approved :: MIT License
Classifier: Operating System :: Microsoft :: Windows
Classifier: Programming Language :: Python :: 3.11
Classifier: Natural Language :: Chinese (Simplified)
License-File: LICENSE
Requires-Dist: mcp<2.0.0,>=1.6.0
Requires-Dist: requests>=2.28.0
Dynamic: author
Dynamic: author-email
Dynamic: classifier
Dynamic: description
Dynamic: description-content-type
Dynamic: download-url
Dynamic: home-page
Dynamic: keywords
Dynamic: license
Dynamic: license-file
Dynamic: requires-dist
Dynamic: summary
